[
  {
    "id": 1,
    "image": "images/card_001.jpg",
    "text": {
      "ru": "Текст к первой карте на русском.",
      "en": "Text for the first card in English."
    }
  },
  {
    "id": 2,
    "image": "images/card_002.jpg",
    "text": {
      "ru": "Текст ко второй карте на русском.",
      "en": "Text for the second card in English."
    }
  },
  {
    "id": 3,
    "image": "images/card_003.jpg",
    "text": {
      "ru": "Текст к третьей карте на русском.",
      "en": "Text for the third card in English."
    }
  }
]